Metadata-Version: 2.1
Name: pytest-bandit-xayon
Version: 0.6.1
Summary: A bandit plugin for pytest
Home-page: https://github.com/Wanderu/pytest-bandit
Author: Wanderu
Author-email: oss@wanderu.com
Maintainer: Matthew Warren
Maintainer-email: mwarren@wanderu.com
License: MIT
Platform: UNKNOWN
Classifier: Development Status :: 4 - Beta
Classifier: Framework :: Pytest
Classifier: Intended Audience :: Developers
Classifier: Topic :: Software Development :: Testing
Classifier: Programming Language :: Python
Classifier: Programming Language :: Python :: 3
Classifier: Programming Language :: Python :: 3.6
Classifier: Programming Language :: Python :: 3.7
Classifier: Programming Language :: Python :: 3.8
Classifier: Programming Language :: Python :: 3.9
Classifier: Programming Language :: Python :: Implementation :: CPython
Classifier: Operating System :: OS Independent
Classifier: License :: OSI Approved :: MIT License
Requires-Python: ~=3.4
License-File: LICENSE
Requires-Dist: bandit (>=1.4.0)
Requires-Dist: pytest (>=3.5.0)
